[{"user_id": "84410011107082240", "settings": null, "metadata": {"team_name": "ricos realm", "mention_pn": "on", "mascot_message_leg_7": "", "mascot_message_leg_5": "Ur mascot is gross", "mascot_message_leg_4": "Thanks for agholor, think I\u2019ll give him the start", "mascot_message_leg_1": "Easy week 1", "mascot_message_emotion_leg_7": "idle", "mascot_message_emotion_leg_5": "idle", "mascot_message_emotion_leg_4": "idle", "mascot_message_emotion_leg_1": "idle", "mascot_item_type_id_leg_9": "andie-luck", "mascot_item_type_id_leg_8": "andie-luck", "mascot_item_type_id_leg_7": "andie-luck", "mascot_item_type_id_leg_6": "andie-luck", "mascot_item_type_id_leg_5": "andie-luck", "mascot_item_type_id_leg_4": "andie-luck", "mascot_item_type_id_leg_3": "andie-luck", "mascot_item_type_id_leg_2": "andie-luck", "mascot_item_type_id_leg_17": "andie-luck", "mascot_item_type_id_leg_16": "andie-luck", "mascot_item_type_id_leg_15": "andie-luck", "mascot_item_type_id_leg_14": "andie-luck", "mascot_item_type_id_leg_13": "andie-luck", "mascot_item_type_id_leg_12": "andie-luck", "mascot_item_type_id_leg_11": "andie-luck", "mascot_item_type_id_leg_10": "andie-luck", "mascot_item_type_id_leg_1": "andie-luck", "allow_pn": "on"}, "league_id": "458672130456809472", "is_owner": false, "is_bot": null, "display_name": "pranav", "avatar": "3954772e0d353b0bef6cfb572a62cf07"}, {"user_id": "94862074874052608", "settings": null, "metadata": {"mascot_item_type_id_leg_6": "panther-man", "mascot_item_type_id_leg_10": "gman", "mascot_message_leg_5": "", "team_name_update": "off", "mention_pn": "on", "mascot_item_type_id_leg_5": "panther-man", "mascot_item_type_id_leg_13": "gman", "team_name": "Gang Green", "allow_pn": "off", "mascot_item_type_id_leg_9": "gman", "mascot_item_type_id_leg_8": "gman", "mascot_item_type_id_leg_7": "gman", "mascot_item_type_id_leg_17": "gman", "mascot_message_leg_7": "Pls Leveon", "mascot_message_emotion_leg_7": "idle", "mascot_item_type_id_leg_12": "gman", "mascot_item_type_id_leg_15": "gman", "user_message_pn": "on", "mascot_message_leg_1": "Pew pew pew", "mascot_message_emotion_leg_5": "idle", "transaction_commissioner": "on", "mascot_message_leg_6": "I\u2019m in danger", "transaction_free_agent": "off", "mascot_message_leg_2": "I\u2019m feeling dangerous", "mascot_item_type_id_leg_4": "gman", "mascot_message_emotion_leg_2": "idle_happy", "transaction_trade": "on", "mascot_message_emotion_leg_6": "idle_sad", "transaction_waiver": "off", "mascot_message_emotion_leg_1": "idle", "mascot_item_type_id_leg_16": "gman", "mascot_item_type_id_leg_11": "gman", "mascot_item_type_id_leg_1": "heavy-metal", "mascot_item_type_id_leg_3": "steel-man", "mascot_message_emotion_leg_3": "idle_nervous", "mascot_message": "on", "mascot_message_leg_4": "Mascot Less", "mascot_item_type_id_leg_14": "gman", "player_nickname_update": "off", "mascot_message_leg_3": "", "mascot_message_emotion_leg_4": "idle_sad", "mascot_item_type_id_leg_2": "panther-man"}, "league_id": "458672130456809472", "is_owner": false, "is_bot": null, "display_name": "adv1996", "avatar": "fed35eef4b71cc48b383db68b9ef0c31"}, {"user_id": "459203311979982848", "settings": null, "metadata": {"mascot_item_type_id_leg_6": "green-gang", "mascot_item_type_id_leg_10": "green-gang", "mascot_message_leg_5": "", "mention_pn": "on", "mascot_item_type_id_leg_5": "green-gang", "mascot_item_type_id_leg_13": "green-gang", "team_name": "RevengeSzn", "allow_pn": "on", "mascot_item_type_id_leg_9": "green-gang", "mascot_item_type_id_leg_8": "green-gang", "mascot_item_type_id_leg_7": "green-gang", "mascot_item_type_id_leg_17": "green-gang", "mascot_message_leg_7": "It\u2019s never over till it\u2019s over bretheren", "mascot_message_emotion_leg_7": "action_hurt02", "mascot_item_type_id_leg_12": "green-gang", "mascot_item_type_id_leg_15": "green-gang", "mascot_message_leg_1": "Better luck week 12", "mascot_message_emotion_leg_5": "idle", "mascot_message_leg_6": "One day the Pats D will fall and your team will turn into ashes and dust", "mascot_message_leg_2": "", "mascot_item_type_id_leg_4": "green-gang", "mascot_message_emotion_leg_6": "idle", "mascot_message_emotion_leg_1": "idle", "mascot_item_type_id_leg_16": "green-gang", "mascot_item_type_id_leg_11": "green-gang", "mascot_item_type_id_leg_1": "green-gang", "mascot_item_type_id_leg_3": "green-gang", "mascot_message_emotion_leg_3": "idle", "mascot_message_leg_4": "Bench Cooper Kupp, introduce some diversity", "mascot_item_type_id_leg_14": "green-gang", "mascot_message_leg_3": "", "mascot_message_emotion_leg_4": "action_joy02", "mascot_item_type_id_leg_2": "green-gang"}, "league_id": "458672130456809472", "is_owner": true, "is_bot": false, "display_name": "ubdtheCommish", "avatar": "5808fda7d6bbad03d9c4d86ad09858de"}, {"user_id": "459204048109694976", "settings": null, "metadata": {"team_name": "Probably shouldnt be 4-2", "mention_pn": "on", "mascot_message_leg_4": "", "mascot_message_leg_3": "Fuck you I counldn\u2019t even read your article", "mascot_message_leg_1": "Your mom", "mascot_message_emotion_leg_4": "idle", "mascot_message_emotion_leg_3": "idle", "mascot_message_emotion_leg_2": "action_joy02", "mascot_message_emotion_leg_1": "action_hurt01", "mascot_item_type_id_leg_9": "elfie", "mascot_item_type_id_leg_8": "elfie", "mascot_item_type_id_leg_7": "elfie", "mascot_item_type_id_leg_6": "elfie", "mascot_item_type_id_leg_5": "elfie", "mascot_item_type_id_leg_4": "elfie", "mascot_item_type_id_leg_3": "elfie", "mascot_item_type_id_leg_2": "elfie", "mascot_item_type_id_leg_17": "elfie", "mascot_item_type_id_leg_16": "elfie", "mascot_item_type_id_leg_15": "elfie", "mascot_item_type_id_leg_14": "elfie", "mascot_item_type_id_leg_13": "elfie", "mascot_item_type_id_leg_12": "elfie", "mascot_item_type_id_leg_11": "elfie", "mascot_item_type_id_leg_10": "elfie", "mascot_item_type_id_leg_1": "machocado", "allow_pn": "on"}, "league_id": "458672130456809472", "is_owner": null, "is_bot": false, "display_name": "psmith999", "avatar": "73f02771734e07c9154768a26a74667b"}, {"user_id": "459204170327519232", "settings": null, "metadata": {"team_name": "Quarter chubb", "mention_pn": "on", "mascot_message_leg_5": "", "mascot_message_leg_4": "October 11th don\u2019t get it twisted", "mascot_message_leg_1": "", "mascot_message_emotion_leg_4": "idle", "mascot_message_emotion_leg_2": "action_joy01", "mascot_message_emotion_leg_1": "idle_happy", "mascot_item_type_id_leg_9": "seke", "mascot_item_type_id_leg_8": "seke", "mascot_item_type_id_leg_7": "seke", "mascot_item_type_id_leg_6": "seke", "mascot_item_type_id_leg_5": "seke", "mascot_item_type_id_leg_4": "seke", "mascot_item_type_id_leg_3": "seke", "mascot_item_type_id_leg_2": "seke", "mascot_item_type_id_leg_17": "seke", "mascot_item_type_id_leg_16": "seke", "mascot_item_type_id_leg_15": "seke", "mascot_item_type_id_leg_14": "seke", "mascot_item_type_id_leg_13": "seke", "mascot_item_type_id_leg_12": "seke", "mascot_item_type_id_leg_11": "seke", "mascot_item_type_id_leg_10": "seke", "mascot_item_type_id_leg_1": "", "allow_pn": "on"}, "league_id": "458672130456809472", "is_owner": false, "is_bot": false, "display_name": "DrUn1ucky", "avatar": "adcd6861dc7027e010ad5b451ecdb2b5"}, {"user_id": "459204239567089664", "settings": null, "metadata": {"team_name": "Qing James", "mention_pn": "on", "mascot_message_leg_7": "", "mascot_message_leg_5": "Scary bad ya", "mascot_message_leg_4": "", "mascot_message_leg_2": "Good luck pal! \ud83d\ude01", "mascot_message_emotion_leg_5": "idle", "mascot_message_emotion_leg_2": "idle", "mascot_item_type_id_leg_9": "chicago-bears", "mascot_item_type_id_leg_8": "chicago-bears", "mascot_item_type_id_leg_7": "chicago-bears", "mascot_item_type_id_leg_6": "chicago-bears", "mascot_item_type_id_leg_5": "chicago-bears", "mascot_item_type_id_leg_4": "chicago-bears", "mascot_item_type_id_leg_3": "chicago-bears", "mascot_item_type_id_leg_2": "chicago-bears", "mascot_item_type_id_leg_17": "chicago-bears", "mascot_item_type_id_leg_16": "chicago-bears", "mascot_item_type_id_leg_15": "chicago-bears", "mascot_item_type_id_leg_14": "chicago-bears", "mascot_item_type_id_leg_13": "chicago-bears", "mascot_item_type_id_leg_12": "chicago-bears", "mascot_item_type_id_leg_11": "chicago-bears", "mascot_item_type_id_leg_10": "chicago-bears", "mascot_item_type_id_leg_1": "trash-panda", "allow_pn": "on"}, "league_id": "458672130456809472", "is_owner": false, "is_bot": false, "display_name": "neelpatil", "avatar": "afe9e28f0fbab615ac3593e8d751ba7f"}, {"user_id": "459213594102329344", "settings": null, "metadata": {"mascot_item_type_id_leg_6": "chum", "mascot_item_type_id_leg_10": "chum", "mascot_message_leg_5": "Can I be the kumar to your Harold", "team_name_update": "on", "mention_pn": "on", "mascot_item_type_id_leg_5": "chum", "mascot_item_type_id_leg_13": "chum", "team_name": "Defense wins \u2018ships", "allow_pn": "on", "mascot_item_type_id_leg_9": "chum", "mascot_item_type_id_leg_8": "chum", "mascot_item_type_id_leg_7": "chum", "mascot_item_type_id_leg_17": "chum", "mascot_message_leg_7": "", "mascot_item_type_id_leg_12": "chum", "mascot_item_type_id_leg_15": "chum", "user_message_pn": "on", "mascot_message_leg_1": "", "mascot_message_emotion_leg_5": "idle_happy", "transaction_commissioner": "on", "transaction_free_agent": "on", "mascot_message_leg_2": "", "mascot_item_type_id_leg_4": "chum", "transaction_trade": "on", "transaction_waiver": "on", "mascot_message_emotion_leg_1": "idle", "mascot_item_type_id_leg_16": "chum", "mascot_item_type_id_leg_11": "chum", "mascot_item_type_id_leg_1": "chum", "mascot_item_type_id_leg_3": "chum", "mascot_message": "on", "mascot_message_leg_4": "", "mascot_item_type_id_leg_14": "chum", "player_nickname_update": "on", "mascot_message_emotion_leg_4": "idle_nervous", "mascot_item_type_id_leg_2": "chum"}, "league_id": "458672130456809472", "is_owner": false, "is_bot": false, "display_name": "cmendpara", "avatar": "01c04ca76901ee11c22403f45cdc2196"}, {"user_id": "459213847593480192", "settings": null, "metadata": {"team_name": "In Lamar We Trust", "mention_pn": "on", "mascot_message_leg_5": "Desegregate your team", "mascot_message_leg_4": "Witten will go off", "mascot_message_leg_1": "", "mascot_message_emotion_leg_5": "idle", "mascot_message_emotion_leg_4": "idle_happy", "mascot_message_emotion_leg_3": "idle_nervous", "mascot_message_emotion_leg_2": "action_hurt02", "mascot_message_emotion_leg_1": "action_joy02", "mascot_item_type_id_leg_9": "cookie-party", "mascot_item_type_id_leg_8": "cookie-party", "mascot_item_type_id_leg_7": "cookie-party", "mascot_item_type_id_leg_6": "cookie-party", "mascot_item_type_id_leg_5": "cookie-party", "mascot_item_type_id_leg_4": "cookie-party", "mascot_item_type_id_leg_3": "cookie-party", "mascot_item_type_id_leg_2": "cookie-party", "mascot_item_type_id_leg_17": "cookie-party", "mascot_item_type_id_leg_16": "cookie-party", "mascot_item_type_id_leg_15": "cookie-party", "mascot_item_type_id_leg_14": "cookie-party", "mascot_item_type_id_leg_13": "cookie-party", "mascot_item_type_id_leg_12": "cookie-party", "mascot_item_type_id_leg_11": "cookie-party", "mascot_item_type_id_leg_10": "cookie-party", "mascot_item_type_id_leg_1": "clown", "allow_pn": "on"}, "league_id": "458672130456809472", "is_owner": false, "is_bot": false, "display_name": "east2wes", "avatar": "405213591fe488220f2f4f79d9cc28eb"}, {"user_id": "459230826802966528", "settings": null, "metadata": {"mascot_item_type_id_leg_6": "seke", "mascot_item_type_id_leg_10": "seke", "mascot_message_leg_5": "", "team_name_update": "on", "mention_pn": "on", "mascot_item_type_id_leg_5": "seke", "mascot_item_type_id_leg_13": "seke", "team_name": "America\u2019s Team", "allow_pn": "on", "mascot_item_type_id_leg_9": "seke", "mascot_item_type_id_leg_8": "seke", "mascot_item_type_id_leg_7": "seke", "mascot_item_type_id_leg_17": "seke", "mascot_item_type_id_leg_12": "seke", "mascot_item_type_id_leg_15": "seke", "user_message_pn": "on", "mascot_message_leg_1": "Rat", "mascot_message_emotion_leg_5": "idle_nervous", "transaction_commissioner": "on", "transaction_free_agent": "on", "mascot_message_leg_2": "Solid showing by McCaffery", "mascot_item_type_id_leg_4": "seke", "mascot_message_emotion_leg_2": "action_joy01", "transaction_trade": "on", "transaction_waiver": "on", "mascot_message_emotion_leg_1": "action_joy02", "mascot_item_type_id_leg_16": "seke", "mascot_item_type_id_leg_11": "seke", "mascot_item_type_id_leg_1": "seke", "mascot_item_type_id_leg_3": "seke", "mascot_message_emotion_leg_3": "idle", "mascot_message": "on", "mascot_message_leg_4": "", "mascot_item_type_id_leg_14": "seke", "player_nickname_update": "on", "mascot_message_leg_3": "You dirty cretin", "mascot_message_emotion_leg_4": "idle_happy", "mascot_item_type_id_leg_2": "seke"}, "league_id": "458672130456809472", "is_owner": null, "is_bot": false, "display_name": "Shahil", "avatar": "44f3b4c9c0ee942dff8b28703a716105"}, {"user_id": "459429256129146880", "settings": null, "metadata": {"team_name": "ATL 69ers", "mention_pn": "on", "mascot_message_leg_6": "", "mascot_message_leg_5": "", "mascot_message_leg_4": "", "mascot_message_leg_2": "", "mascot_message_emotion_leg_5": "idle", "mascot_item_type_id_leg_5": "", "allow_pn": "on"}, "league_id": "458672130456809472", "is_owner": null, "is_bot": false, "display_name": "jbick3", "avatar": "0b99d6cc26aa7519e37cdfb269184da3"}, {"user_id": "459439456710029312", "settings": null, "metadata": {"mention_pn": "on", "mascot_message_leg_6": "", "mascot_message_leg_4": "", "mascot_message_leg_1": "", "allow_pn": "on"}, "league_id": "458672130456809472", "is_owner": null, "is_bot": false, "display_name": "derrickbhole", "avatar": "4fb394f49d806fbad75dd79ecc68f525"}, {"user_id": "459443167217840128", "settings": null, "metadata": {"team_name": "Ratty Rats", "mention_pn": "on", "mascot_message_leg_7": "Can\u2019t wait for the finale of the taco bowl tonight", "mascot_message_leg_5": "Boy he\u2019s got gall, man!", "mascot_message_leg_4": "Welcome to the 0-4 Club: Population - Neel Patil", "mascot_message_leg_1": "", "mascot_message_emotion_leg_7": "idle", "mascot_message_emotion_leg_5": "idle", "mascot_message_emotion_leg_4": "action_joy02", "mascot_message_emotion_leg_1": "action_hurt02", "mascot_item_type_id_leg_9": "trash", "mascot_item_type_id_leg_8": "trash", "mascot_item_type_id_leg_7": "trash", "mascot_item_type_id_leg_6": "trash", "mascot_item_type_id_leg_5": "trash", "mascot_item_type_id_leg_4": "trash", "mascot_item_type_id_leg_3": "trash", "mascot_item_type_id_leg_2": "trash", "mascot_item_type_id_leg_17": "trash", "mascot_item_type_id_leg_16": "trash", "mascot_item_type_id_leg_15": "trash", "mascot_item_type_id_leg_14": "trash", "mascot_item_type_id_leg_13": "trash", "mascot_item_type_id_leg_12": "trash", "mascot_item_type_id_leg_11": "trash", "mascot_item_type_id_leg_10": "trash", "mascot_item_type_id_leg_1": "trash", "allow_pn": "on"}, "league_id": "458672130456809472", "is_owner": null, "is_bot": false, "display_name": "BuzzBoy", "avatar": "2892c880ba6c8384e628e50639dd8809"}]