[{"starters": ["1029", "5850", "5052", "4983", "4040", "5012", "4951", "4227", "PIT"], "roster_id": 1, "points": 98.63999938964844, "players": ["PIT", "96", "5850", "538", "5052", "5012", "4983", "4951", "4666", "4455", "4227", "4068", "4040", "3157", "2749", "1029"], "matchup_id": 4, "custom_points": null}, {"starters": ["2028", "2320", "4187", "2583", "1825", "4089", "1071", "1264", "IND"], "roster_id": 2, "points": 80.77999877929688, "players": ["IND", "5857", "4994", "4943", "4866", "4273", "4187", "4089", "2583", "2320", "2028", "1825", "1264", "1110", "1071"], "matchup_id": 5, "custom_points": null}, {"starters": ["4046", "4988", "2315", "2238", "4319", "2505", "2449", "6528", "SF"], "roster_id": 3, "points": 125.77999877929688, "players": ["SF", "6528", "4988", "4319", "4066", "4046", "3306", "3225", "2505", "2449", "2319", "2315", "2238", "1166", "1144", "1049"], "matchup_id": 3, "custom_points": null}, {"starters": ["4984", "4029", "1848", "5872", "344", "1339", "367", "899", "NO"], "roster_id": 4, "points": 129.63999938964844, "players": ["NO", "899", "830", "676", "6149", "5872", "5107", "4984", "4171", "4029", "367", "344", "3200", "2168", "1848", "1339"], "matchup_id": 2, "custom_points": null}, {"starters": ["289", "4035", "2378", "947", "1817", "58", "1408", "4958", "OAK"], "roster_id": 5, "points": 108.72000122070312, "players": ["OAK", "947", "642", "6039", "58", "560", "4958", "4035", "289", "2378", "2257", "1817", "167", "1476", "1408", "1244"], "matchup_id": 1, "custom_points": null}, {"starters": ["4881", "5170", "4018", "5848", "5937", "1592", "943", "2671", "CAR"], "roster_id": 6, "points": 85.27999877929688, "players": ["CHI", "CAR", "943", "5987", "5937", "5848", "5846", "5170", "4881", "4018", "2671", "2381", "2374", "2306", "2197", "1592"], "matchup_id": 6, "custom_points": null}, {"starters": ["331", "4152", "4137", "2216", "1479", "2118", "4082", "6083", "MIN"], "roster_id": 7, "points": 77.31999969482422, "players": ["MIN", "GB", "6083", "5927", "4152", "4146", "4137", "4082", "4033", "3664", "331", "2452", "2216", "2118", "1479", "1234"], "matchup_id": 6, "custom_points": null}, {"starters": ["3294", "4098", "2382", "3199", "2309", "3214", "2078", "3678", "BUF"], "roster_id": 8, "points": 113.36000061035156, "players": ["NYG", "CLE", "BUF", "5038", "4098", "3678", "3294", "3214", "3199", "3198", "2391", "2382", "2309", "2078", "184", "1706"], "matchup_id": 3, "custom_points": null}, {"starters": ["3161", "1833", "956", "4981", "1426", "1466", "6151", "120", "DAL"], "roster_id": 9, "points": 106.26000213623047, "players": ["DAL", "956", "6151", "5917", "5844", "4981", "4199", "4149", "3161", "1837", "1833", "1466", "1426", "120", "1149"], "matchup_id": 5, "custom_points": null}, {"starters": ["24", "4034", "3969", "4131", "4039", "1388", "4949", "17", "NYJ"], "roster_id": 10, "points": 90.94000244140625, "players": ["NYJ", "963", "5046", "4950", "4949", "4131", "4039", "4034", "3969", "3202", "2747", "24", "17", "1689", "1388"], "matchup_id": 1, "custom_points": null}, {"starters": ["4017", "3164", "6130", "4037", "2410", "1587", "5045", "4233", "NE"], "roster_id": 11, "points": 101.08000183105469, "players": ["NE", "6130", "6007", "5967", "5068", "5045", "4233", "4217", "4037", "4017", "3242", "3164", "2410", "223", "1587", "1352"], "matchup_id": 2, "custom_points": null}, {"starters": ["5127", "4663", "5892", "1067", "1992", "4055", "3321", "1266", "LAR"], "roster_id": 12, "points": 63.79999923706055, "players": ["LAR", "5892", "5849", "5127", "4962", "4892", "4663", "4421", "4157", "4055", "3321", "2133", "1992", "1266", "1067"], "matchup_id": 4, "custom_points": null}]